verilog_fpga_simulation/blocks/4_bit_cla/4_bit_cla.v
`timescale 1ns/1ps

module bit_4_cla(a, b, cin, sum, cout);
    input [3:0] a, b;
    input cin;
    output [3:0] sum;
    output cout;
    wire [3:0] g, p;
    wire c1, c2, c3;

    and g0 (g[0], a[0], b[0]);
    and g1 (g[1], a[1], b[1]);
    and g2 (g[2], a[2], b[2]);
    and g3 (g[3], a[3], b[3]);

    xor p0 (p[0], a[0], b[0]);
    xor p1 (p[1], a[1], b[1]);
    xor p2 (p[2], a[2], b[2]);
    xor p3 (p[3], a[3], b[3]);

    wire temp1, temp2, temp3, temp4, temp5, temp6;

    // c1 = g0 + (p0 * cin)
    and and_c1 (temp1, p[0], cin);
    or or_c1 (c1, g[0], temp1);

    // c2 = g1 + (p1 * g0) + (p1 * p0 * cin)
    and and_c2_1 (temp2, p[1], g[0]);
    and and_c2_2 (temp3, p[1], p[0], cin);
    or or_c2 (c2, g[1], temp2, temp3);

    // c3 = g2 + (p2 * g1) + (p2 * p1 * g0) + (p2 * p1 * p0 * cin)
    and and_c3_1 (temp4, p[2], g[1]);
    and and_c3_2 (temp5, p[2], p[1], g[0]);
    and and_c3_3 (temp6, p[2], p[1], p[0], cin);
    or or_c3 (c3, g[2], temp4, temp5, temp6);

    // cout = g3 + (p3 * g2) + (p3 * p2 * g1) + (p3 * p2 * p1 * g0) + (p3 * p2 * p1 * p0 * cin)
    wire temp7, temp8, temp9, temp10;
    and and_cout_1 (temp7, p[3], g[2]);
    and and_cout_2 (temp8, p[3], p[2], g[1]);
    and and_cout_3 (temp9, p[3], p[2], p[1], g[0]);
    and and_cout_4 (temp10, p[3], p[2], p[1], p[0], cin);
    or or_cout (cout, g[3], temp7, temp8, temp9, temp10);

    xor sum0 (sum[0], p[0], cin);
    xor sum1 (sum[1], p[1], c1);
    xor sum2 (sum[2], p[2], c2);
    xor sum3 (sum[3], p[3], c3);
endmodule

fpga_simulation/blocks/4_bit_cla/4_bit_cla_test.v
`timescale 1ns/1ps

module bit_4_cla_test;
    reg [3:0] a, b;
    reg cin;
    wire [3:0] sum;
    wire cout;

    bit_4_cla inst1(
        .a(a),
        .b(b),
        .cin(cin),
        .sum(sum),
        .cout(cout)
    );

    initial begin
        $dumpfile("bit_4_cla_test.vcd");
        $dumpvars(0, bit_4_cla_test);
        
        a = 4'b0000; b = 4'b0000; cin = 1'b0;
        #2560 $finish;
    end
    always #5 a[0] = ~a[0];
    always #10 a[1] = ~a[1];
    always #20 a[2] = ~a[2];
    always #40 a[3] = ~a[3];
    always #80 b[0] = ~b[0];
    always #160 b[1] = ~b[1];
    always #320 b[2] = ~b[2];
    always #640 b[3] = ~b[3];
    always #1280 cin = ~cin;

    always @(a)
    $display("a=%b, b=%b, cin=%b, sum=%b, cout=%b", a, b, cin, sum, cout);
endmodule

verilog_fpga_simulation/blocks/4_bit_cla/bit_4_cla_test.vcd
$date
	Wed Nov 20 00:11:38 2024
$end
$version
	Icarus Verilog
$end
$timescale
	1ps
$end
$scope module bit_4_cla_test $end
$var wire 4 ! sum [3:0] $end
$var wire 1 " cout $end
$var reg 4 # a [3:0] $end
$var reg 4 $ b [3:0] $end
$var reg 1 % cin $end
$scope module inst1 $end
$var wire 4 & a [3:0] $end
$var wire 4 ' b [3:0] $end
$var wire 1 ( c1 $end
$var wire 1 ) c2 $end
$var wire 1 * c3 $end
$var wire 1 % cin $end
$var wire 1 " cout $end
$var wire 1 + temp1 $end
$var wire 1 , temp10 $end
$var wire 1 - temp2 $end
$var wire 1 . temp3 $end
$var wire 1 / temp4 $end
$var wire 1 0 temp5 $end
$var wire 1 1 temp6 $end
$var wire 1 2 temp7 $end
$var wire 1 3 temp8 $end
$var wire 1 4 temp9 $end
$var wire 4 5 sum [3:0] $end
$var wire 4 6 p [3:0] $end
$var wire 4 7 g [3:0] $end
$upscope $end
$upscope $end
$enddefinitions $end
#0
$dumpvars
b0 7
b0 6
b0 5
04
03
02
01
00
0/
0.
0-
0,
0+
0*
0)
0(
b0 '
b0 &
0%
b0 $
b0 #
0"
b0 !
$end
#5000
b1 !
b1 5
b1 6
b1 #
b1 &
#10000
b10 !
b10 5
b10 6
b10 #
b10 &
#15000
b11 !
b11 5
b11 6
b11 #
b11 &
#20000
b100 !
b100 5
b100 6
b100 #
b100 &
#25000
b101 !
b101 5
b101 6
b101 #
b101 &
#30000
b110 !
b110 5
b110 6
b110 #
b110 &
#35000
b111 !
b111 5
b111 6
b111 #
b111 &
#40000
b1000 !
b1000 5
b1000 6
b1000 #
b1000 &
#45000
b1001 !
b1001 5
b1001 6
b1001 #
b1001 &
#50000
b1010 !
b1010 5
b1010 6
b1010 #
b1010 &
#55000
b1011 !
b1011 5
b1011 6
b1011 #
b1011 &
#60000
b1100 !
b1100 5
b1100 6
b1100 #
b1100 &
#65000
b1101 !
b1101 5
b1101 6
b1101 #
b1101 &
#70000
b1110 !
b1110 5
b1110 6
b1110 #
b1110 &
#75000
b1111 !
b1111 5
b1111 6
b1111 #
b1111 &
#80000
b1 !
b1 5
b1 6
b0 #
b0 &
b1 $
b1 '
#85000
1(
b10 !
b10 5
b1 7
b0 6
b1 #
b1 &
#90000
0(
b11 !
b11 5
b0 7
b11 6
b10 #
b10 &
#95000
1)
1(
1-
b100 !
b100 5
b1 7
b10 6
b11 #
b11 &
#100000
0)
0(
0-
b101 !
b101 5
b0 7
b101 6
b100 #
b100 &
#105000
1(
b110 !
b110 5
b1 7
b100 6
b101 #
b101 &
#110000
0(
b111 !
b111 5
b0 7
b111 6
b110 #
b110 &
#115000
1)
1*
1(
1-
10
b1000 !
b1000 5
b1 7
b110 6
b111 #
b111 &
#120000
0)
0*
0(
0-
00
b1001 !
b1001 5
b0 7
b1001 6
b1000 #
b1000 &
#125000
1(
b1010 !
b1010 5
b1 7
b1000 6
b1001 #
b1001 &
#130000
0(
b1011 !
b1011 5
b0 7
b1011 6
b1010 #
b1010 &
#135000
1)
1(
1-
b1100 !
b1100 5
b1 7
b1010 6
b1011 #
b1011 &
#140000
0)
0(
0-
b1101 !
b1101 5
b0 7
b1101 6
b1100 #
b1100 &
#145000
1(
b1110 !
b1110 5
b1 7
b1100 6
b1101 #
b1101 &
#150000
0(
b1111 !
b1111 5
b0 7
b1111 6
b1110 #
b1110 &
#155000
1"
1)
1*
1(
1-
10
14
b0 !
b0 5
b1 7
b1110 6
b1111 #
b1111 &
#160000
0"
0)
0*
b10 !
b10 5
0(
0-
00
04
b10 6
b0 7
b0 #
b0 &
b10 $
b10 '
#165000
b11 !
b11 5
b11 6
b1 #
b1 &
#170000
1)
b100 !
b100 5
b10 7
b0 6
b10 #
b10 &
#175000
b101 !
b101 5
b1 6
b11 #
b11 &
#180000
0)
b110 !
b110 5
b0 7
b110 6
b100 #
b100 &
#185000
b111 !
b111 5
b111 6
b101 #
b101 &
#190000
1*
1)
1/
b1000 !
b1000 5
b10 7
b100 6
b110 #
b110 &
#195000
b1001 !
b1001 5
b101 6
b111 #
b111 &
#200000
0*
0)
0/
b1010 !
b1010 5
b0 7
b1010 6
b1000 #
b1000 &
#205000
b1011 !
b1011 5
b1011 6
b1001 #
b1001 &
#210000
1)
b1100 !
b1100 5
b10 7
b1000 6
b1010 #
b1010 &
#215000
b1101 !
b1101 5
b1001 6
b1011 #
b1011 &
#220000
0)
b1110 !
b1110 5
b0 7
b1110 6
b1100 #
b1100 &
#225000
b1111 !
b1111 5
b1111 6
b1101 #
b1101 &
#230000
1"
1*
1)
1/
13
b0 !
b0 5
b10 7
b1100 6
b1110 #
b1110 &
#235000
b1 !
b1 5
b1101 6
b1111 #
b1111 &
#240000
0"
0*
0)
0/
03
b11 !
b11 5
b0 7
b11 6
b0 #
b0 &
b11 $
b11 '
#245000
1)
1(
1-
b100 !
b100 5
b1 7
b10 6
b1 #
b1 &
#250000
0(
0-
b101 !
b101 5
b10 7
b1 6
b10 #
b10 &
#255000
1(
b110 !
b110 5
b11 7
b0 6
b11 #
b11 &
#260000
0(
0)
b111 !
b111 5
b0 7
b111 6
b100 #
b100 &
#265000
1)
1*
1(
1-
10
b1000 !
b1000 5
b1 7
b110 6
b101 #
b101 &
#270000
0(
1/
0-
00
b1001 !
b1001 5
b10 7
b101 6
b110 #
b110 &
#275000
1(
b1010 !
b1010 5
b11 7
b100 6
b111 #
b111 &
#280000
0*
0(
0)
0/
b1011 !
b1011 5
b0 7
b1011 6
b1000 #
b1000 &
#285000
1)
1(
1-
b1100 !
b1100 5
b1 7
b1010 6
b1001 #
b1001 &
#290000
0(
0-
b1101 !
b1101 5
b10 7
b1001 6
b1010 #
b1010 &
#295000
1(
b1110 !
b1110 5
b11 7
b1000 6
b1011 #
b1011 &
#300000
0(
0)
b1111 !
b1111 5
b0 7
b1111 6
b1100 #
b1100 &
#305000
1"
1)
1*
1(
1-
10
14
b0 !
b0 5
b1 7
b1110 6
b1101 #
b1101 &
#310000
0(
1/
13
0-
00
04
b1 !
b1 5
b10 7
b1101 6
b1110 #
b1110 &
#315000
1(
b10 !
b10 5
b11 7
b1100 6
b1111 #
b1111 &
#320000
0"
0*
b100 !
b100 5
0(
0)
0/
03
b100 6
b0 7
b0 #
b0 &
b100 $
b100 '
#325000
b101 !
b101 5
b101 6
b1 #
b1 &
#330000
b110 !
b110 5
b110 6
b10 #
b10 &
#335000
b111 !
b111 5
b111 6
b11 #
b11 &
#340000
1*
b1000 !
b1000 5
b100 7
b0 6
b100 #
b100 &
#345000
b1001 !
b1001 5
b1 6
b101 #
b101 &
#350000
b1010 !
b1010 5
b10 6
b110 #
b110 &
#355000
b1011 !
b1011 5
b11 6
b111 #
b111 &
#360000
0*
b1100 !
b1100 5
b0 7
b1100 6
b1000 #
b1000 &
#365000
b1101 !
b1101 5
b1101 6
b1001 #
b1001 &
#370000
b1110 !
b1110 5
b1110 6
b1010 #
b1010 &
#375000
b1111 !
b1111 5
b1111 6
b1011 #
b1011 &
#380000
1"
1*
12
b0 !
b0 5
b100 7
b1000 6
b1100 #
b1100 &
#385000
b1 !
b1 5
b1001 6
b1101 #
b1101 &
#390000
b10 !
b10 5
b1010 6
b1110 #
b1110 &
#395000
b11 !
b11 5
b1011 6
b1111 #
b1111 &
#400000
0"
0*
02
b101 !
b101 5
b0 7
b101 6
b0 #
b0 &
b101 $
b101 '
#405000
1(
b110 !
b110 5
b1 7
b100 6
b1 #
b1 &
#410000
0(
b111 !
b111 5
b0 7
b111 6
b10 #
b10 &
#415000
1)
1*
1(
1-
10
b1000 !
b1000 5
b1 7
b110 6
b11 #
b11 &
#420000
0)
0(
0-
00
b1001 !
b1001 5
b100 7
b1 6
b100 #
b100 &
#425000
1(
b1010 !
b1010 5
b101 7
b0 6
b101 #
b101 &
#430000
0(
b1011 !
b1011 5
b100 7
b11 6
b110 #
b110 &
#435000
1)
1(
1-
b1100 !
b1100 5
b101 7
b10 6
b111 #
b111 &
#440000
0)
0(
0-
0*
b1101 !
b1101 5
b0 7
b1101 6
b1000 #
b1000 &
#445000
1(
b1110 !
b1110 5
b1 7
b1100 6
b1001 #
b1001 &
#450000
0(
b1111 !
b1111 5
b0 7
b1111 6
b1010 #
b1010 &
#455000
1"
1)
1*
1(
1-
10
14
b0 !
b0 5
b1 7
b1110 6
b1011 #
b1011 &
#460000
0)
0(
0-
12
00
04
b1 !
b1 5
b100 7
b1001 6
b1100 #
b1100 &
#465000
1(
b10 !
b10 5
b101 7
b1000 6
b1101 #
b1101 &
#470000
0(
b11 !
b11 5
b100 7
b1011 6
b1110 #
b1110 &
#475000
1)
1(
1-
b100 !
b100 5
b101 7
b1010 6
b1111 #
b1111 &
#480000
0"
0)
0*
02
b110 !
b110 5
0(
0-
b110 6
b0 7
b0 #
b0 &
b110 $
b110 '
#485000
b111 !
b111 5
b111 6
b1 #
b1 &
#490000
1*
1)
1/
b1000 !
b1000 5
b10 7
b100 6
b10 #
b10 &
#495000
b1001 !
b1001 5
b101 6
b11 #
b11 &
#500000
0)
0/
b1010 !
b1010 5
b100 7
b10 6
b100 #
b100 &
#505000
b1011 !
b1011 5
b11 6
b101 #
b101 &
#510000
1)
b1100 !
b1100 5
b110 7
b0 6
b110 #
b110 &
#515000
b1101 !
b1101 5
b1 6
b111 #
b111 &
#520000
0)
0*
b1110 !
b1110 5
b0 7
b1110 6
b1000 #
b1000 &
#525000
b1111 !
b1111 5
b1111 6
b1001 #
b1001 &
#530000
1"
1*
1)
1/
13
b0 !
b0 5
b10 7
b1100 6
b1010 #
b1010 &
#535000
b1 !
b1 5
b1101 6
b1011 #
b1011 &
#540000
0)
12
0/
03
b10 !
b10 5
b100 7
b1010 6
b1100 #
b1100 &
#545000
b11 !
b11 5
b1011 6
b1101 #
b1101 &
#550000
1)
b100 !
b100 5
b110 7
b1000 6
b1110 #
b1110 &
#555000
b101 !
b101 5
b1001 6
b1111 #
b1111 &
#560000
0"
0)
0*
02
b111 !
b111 5
b0 7
b111 6
b0 #
b0 &
b111 $
b111 '
#565000
1)
1*
1(
1-
10
b1000 !
b1000 5
b1 7
b110 6
b1 #
b1 &
#570000
0(
1/
0-
00
b1001 !
b1001 5
b10 7
b101 6
b10 #
b10 &
#575000
1(
b1010 !
b1010 5
b11 7
b100 6
b11 #
b11 &
#580000
0(
0)
0/
b1011 !
b1011 5
b100 7
b11 6
b100 #
b100 &
#585000
1)
1(
1-
b1100 !
b1100 5
b101 7
b10 6
b101 #
b101 &
#590000
0(
0-
b1101 !
b1101 5
b110 7
b1 6
b110 #
b110 &
#595000
1(
b1110 !
b1110 5
b111 7
b0 6
b111 #
b111 &
#600000
0(
0)
0*
b1111 !
b1111 5
b0 7
b1111 6
b1000 #
b1000 &
#605000
1"
1)
1*
1(
1-
10
14
b0 !
b0 5
b1 7
b1110 6
b1001 #
b1001 &
#610000
0(
1/
13
0-
00
04
b1 !
b1 5
b10 7
b1101 6
b1010 #
b1010 &
#615000
1(
b10 !
b10 5
b11 7
b1100 6
b1011 #
b1011 &
#620000
0(
0)
12
0/
03
b11 !
b11 5
b100 7
b1011 6
b1100 #
b1100 &
#625000
1)
1(
1-
b100 !
b100 5
b101 7
b1010 6
b1101 #
b1101 &
#630000
0(
0-
b101 !
b101 5
b110 7
b1001 6
b1110 #
b1110 &
#635000
1(
b110 !
b110 5
b111 7
b1000 6
b1111 #
b1111 &
#640000
0"
b1000 !
b1000 5
0(
0)
0*
02
b0 7
b0 #
b0 &
b1000 $
b1000 '
#645000
b1001 !
b1001 5
b1001 6
b1 #
b1 &
#650000
b1010 !
b1010 5
b1010 6
b10 #
b10 &
#655000
b1011 !
b1011 5
b1011 6
b11 #
b11 &
#660000
b1100 !
b1100 5
b1100 6
b100 #
b100 &
#665000
b1101 !
b1101 5
b1101 6
b101 #
b101 &
#670000
b1110 !
b1110 5
b1110 6
b110 #
b110 &
#675000
b1111 !
b1111 5
b1111 6
b111 #
b111 &
#680000
1"
b0 !
b0 5
b1000 7
b0 6
b1000 #
b1000 &
#685000
b1 !
b1 5
b1 6
b1001 #
b1001 &
#690000
b10 !
b10 5
b10 6
b1010 #
b1010 &
#695000
b11 !
b11 5
b11 6
b1011 #
b1011 &
#700000
b100 !
b100 5
b100 6
b1100 #
b1100 &
#705000
b101 !
b101 5
b101 6
b1101 #
b1101 &
#710000
b110 !
b110 5
b110 6
b1110 #
b1110 &
#715000
b111 !
b111 5
b111 6
b1111 #
b1111 &
#720000
0"
b1001 !
b1001 5
b0 7
b1001 6
b0 #
b0 &
b1001 $
b1001 '
#725000
1(
b1010 !
b1010 5
b1 7
b1000 6
b1 #
b1 &
#730000
0(
b1011 !
b1011 5
b0 7
b1011 6
b10 #
b10 &
#735000
1)
1(
1-
b1100 !
b1100 5
b1 7
b1010 6
b11 #
b11 &
#740000
0)
0(
0-
b1101 !
b1101 5
b0 7
b1101 6
b100 #
b100 &
#745000
1(
b1110 !
b1110 5
b1 7
b1100 6
b101 #
b101 &
#750000
0(
b1111 !
b1111 5
b0 7
b1111 6
b110 #
b110 &
#755000
1"
1)
1*
1(
1-
10
14
b0 !
b0 5
b1 7
b1110 6
b111 #
b111 &
#760000
0)
0*
0(
0-
00
04
b1 !
b1 5
b1000 7
b1 6
b1000 #
b1000 &
#765000
1(
b10 !
b10 5
b1001 7
b0 6
b1001 #
b1001 &
#770000
0(
b11 !
b11 5
b1000 7
b11 6
b1010 #
b1010 &
#775000
1)
1(
1-
b100 !
b100 5
b1001 7
b10 6
b1011 #
b1011 &
#780000
0)
0(
0-
b101 !
b101 5
b1000 7
b101 6
b1100 #
b1100 &
#785000
1(
b110 !
b110 5
b1001 7
b100 6
b1101 #
b1101 &
#790000
0(
b111 !
b111 5
b1000 7
b111 6
b1110 #
b1110 &
#795000
1)
1*
1(
1-
10
b1000 !
b1000 5
b1001 7
b110 6
b1111 #
b1111 &
#800000
0"
0)
0*
b1010 !
b1010 5
0(
0-
00
b1010 6
b0 7
b0 #
b0 &
b1010 $
b1010 '
#805000
b1011 !
b1011 5
b1011 6
b1 #
b1 &
#810000
1)
b1100 !
b1100 5
b10 7
b1000 6
b10 #
b10 &
#815000
b1101 !
b1101 5
b1001 6
b11 #
b11 &
#820000
0)
b1110 !
b1110 5
b0 7
b1110 6
b100 #
b100 &
#825000
b1111 !
b1111 5
b1111 6
b101 #
b101 &
#830000
1"
1*
1)
1/
13
b0 !
b0 5
b10 7
b1100 6
b110 #
b110 &
#835000
b1 !
b1 5
b1101 6
b111 #
b111 &
#840000
0*
0)
0/
03
b10 !
b10 5
b1000 7
b10 6
b1000 #
b1000 &
#845000
b11 !
b11 5
b11 6
b1001 #
b1001 &
#850000
1)
b100 !
b100 5
b1010 7
b0 6
b1010 #
b1010 &
#855000
b101 !
b101 5
b1 6
b1011 #
b1011 &
#860000
0)
b110 !
b110 5
b1000 7
b110 6
b1100 #
b1100 &
#865000
b111 !
b111 5
b111 6
b1101 #
b1101 &
#870000
1*
1)
1/
b1000 !
b1000 5
b1010 7
b100 6
b1110 #
b1110 &
#875000
b1001 !
b1001 5
b101 6
b1111 #
b1111 &
#880000
0*
0"
0)
0/
b1011 !
b1011 5
b0 7
b1011 6
b0 #
b0 &
b1011 $
b1011 '
#885000
1)
1(
1-
b1100 !
b1100 5
b1 7
b1010 6
b1 #
b1 &
#890000
0(
0-
b1101 !
b1101 5
b10 7
b1001 6
b10 #
b10 &
#895000
1(
b1110 !
b1110 5
b11 7
b1000 6
b11 #
b11 &
#900000
0(
0)
b1111 !
b1111 5
b0 7
b1111 6
b100 #
b100 &
#905000
1"
1)
1*
1(
1-
10
14
b0 !
b0 5
b1 7
b1110 6
b101 #
b101 &
#910000
0(
1/
13
0-
00
04
b1 !
b1 5
b10 7
b1101 6
b110 #
b110 &
#915000
1(
b10 !
b10 5
b11 7
b1100 6
b111 #
b111 &
#920000
0*
0(
0)
0/
03
b11 !
b11 5
b1000 7
b11 6
b1000 #
b1000 &
#925000
1)
1(
1-
b100 !
b100 5
b1001 7
b10 6
b1001 #
b1001 &
#930000
0(
0-
b101 !
b101 5
b1010 7
b1 6
b1010 #
b1010 &
#935000
1(
b110 !
b110 5
b1011 7
b0 6
b1011 #
b1011 &
#940000
0(
0)
b111 !
b111 5
b1000 7
b111 6
b1100 #
b1100 &
#945000
1)
1*
1(
1-
10
b1000 !
b1000 5
b1001 7
b110 6
b1101 #
b1101 &
#950000
0(
1/
0-
00
b1001 !
b1001 5
b1010 7
b101 6
b1110 #
b1110 &
#955000
1(
b1010 !
b1010 5
b1011 7
b100 6
b1111 #
b1111 &
#960000
0"
0*
b1100 !
b1100 5
0(
0)
0/
b1100 6
b0 7
b0 #
b0 &
b1100 $
b1100 '
#965000
b1101 !
b1101 5
b1101 6
b1 #
b1 &
#970000
b1110 !
b1110 5
b1110 6
b10 #
b10 &
#975000
b1111 !
b1111 5
b1111 6
b11 #
b11 &
#980000
1"
1*
12
b0 !
b0 5
b100 7
b1000 6
b100 #
b100 &
#985000
b1 !
b1 5
b1001 6
b101 #
b101 &
#990000
b10 !
b10 5
b1010 6
b110 #
b110 &
#995000
b11 !
b11 5
b1011 6
b111 #
b111 &
#1000000
0*
02
b100 !
b100 5
b1000 7
b100 6
b1000 #
b1000 &
#1005000
b101 !
b101 5
b101 6
b1001 #
b1001 &
#1010000
b110 !
b110 5
b110 6
b1010 #
b1010 &
#1015000
b111 !
b111 5
b111 6
b1011 #
b1011 &
#1020000
1*
b1000 !
b1000 5
b1100 7
b0 6
b1100 #
b1100 &
#1025000
b1001 !
b1001 5
b1 6
b1101 #
b1101 &
#1030000
b1010 !
b1010 5
b10 6
b1110 #
b1110 &
#1035000
b1011 !
b1011 5
b11 6
b1111 #
b1111 &
#1040000
0"
0*
b1101 !
b1101 5
b0 7
b1101 6
b0 #
b0 &
b1101 $
b1101 '
#1045000
1(
b1110 !
b1110 5
b1 7
b1100 6
b1 #
b1 &
#1050000
0(
b1111 !
b1111 5
b0 7
b1111 6
b10 #
b10 &
#1055000
1"
1)
1*
1(
1-
10
14
b0 !
b0 5
b1 7
b1110 6
b11 #
b11 &
#1060000
0)
0(
0-
12
00
04
b1 !
b1 5
b100 7
b1001 6
b100 #
b100 &
#1065000
1(
b10 !
b10 5
b101 7
b1000 6
b101 #
b101 &
#1070000
0(
b11 !
b11 5
b100 7
b1011 6
b110 #
b110 &
#1075000
1)
1(
1-
b100 !
b100 5
b101 7
b1010 6
b111 #
b111 &
#1080000
0)
0(
0-
0*
02
b101 !
b101 5
b1000 7
b101 6
b1000 #
b1000 &
#1085000
1(
b110 !
b110 5
b1001 7
b100 6
b1001 #
b1001 &
#1090000
0(
b111 !
b111 5
b1000 7
b111 6
b1010 #
b1010 &
#1095000
1)
1*
1(
1-
10
b1000 !
b1000 5
b1001 7
b110 6
b1011 #
b1011 &
#1100000
0)
0(
0-
00
b1001 !
b1001 5
b1100 7
b1 6
b1100 #
b1100 &
#1105000
1(
b1010 !
b1010 5
b1101 7
b0 6
b1101 #
b1101 &
#1110000
0(
b1011 !
b1011 5
b1100 7
b11 6
b1110 #
b1110 &
#1115000
1)
1(
1-
b1100 !
b1100 5
b1101 7
b10 6
b1111 #
b1111 &
#1120000
0"
0)
0*
b1110 !
b1110 5
0(
0-
b1110 6
b0 7
b0 #
b0 &
b1110 $
b1110 '
#1125000
b1111 !
b1111 5
b1111 6
b1 #
b1 &
#1130000
1"
1*
1)
1/
13
b0 !
b0 5
b10 7
b1100 6
b10 #
b10 &
#1135000
b1 !
b1 5
b1101 6
b11 #
b11 &
#1140000
0)
12
0/
03
b10 !
b10 5
b100 7
b1010 6
b100 #
b100 &
#1145000
b11 !
b11 5
b1011 6
b101 #
b101 &
#1150000
1)
b100 !
b100 5
b110 7
b1000 6
b110 #
b110 &
#1155000
b101 !
b101 5
b1001 6
b111 #
b111 &
#1160000
0)
0*
02
b110 !
b110 5
b1000 7
b110 6
b1000 #
b1000 &
#1165000
b111 !
b111 5
b111 6
b1001 #
b1001 &
#1170000
1*
1)
1/
b1000 !
b1000 5
b1010 7
b100 6
b1010 #
b1010 &
#1175000
b1001 !
b1001 5
b101 6
b1011 #
b1011 &
#1180000
0)
0/
b1010 !
b1010 5
b1100 7
b10 6
b1100 #
b1100 &
#1185000
b1011 !
b1011 5
b11 6
b1101 #
b1101 &
#1190000
1)
b1100 !
b1100 5
b1110 7
b0 6
b1110 #
b1110 &
#1195000
b1101 !
b1101 5
b1 6
b1111 #
b1111 &
#1200000
0"
0)
0*
b1111 !
b1111 5
b0 7
b1111 6
b0 #
b0 &
b1111 $
b1111 '
#1205000
1"
1)
1*
1(
1-
10
14
b0 !
b0 5
b1 7
b1110 6
b1 #
b1 &
#1210000
0(
1/
13
0-
00
04
b1 !
b1 5
b10 7
b1101 6
b10 #
b10 &
#1215000
1(
b10 !
b10 5
b11 7
b1100 6
b11 #
b11 &
#1220000
0(
0)
12
0/
03
b11 !
b11 5
b100 7
b1011 6
b100 #
b100 &
#1225000
1)
1(
1-
b100 !
b100 5
b101 7
b1010 6
b101 #
b101 &
#1230000
0(
0-
b101 !
b101 5
b110 7
b1001 6
b110 #
b110 &
#1235000
1(
b110 !
b110 5
b111 7
b1000 6
b111 #
b111 &
#1240000
0(
0)
0*
02
b111 !
b111 5
b1000 7
b111 6
b1000 #
b1000 &
#1245000
1)
1*
1(
1-
10
b1000 !
b1000 5
b1001 7
b110 6
b1001 #
b1001 &
#1250000
0(
1/
0-
00
b1001 !
b1001 5
b1010 7
b101 6
b1010 #
b1010 &
#1255000
1(
b1010 !
b1010 5
b1011 7
b100 6
b1011 #
b1011 &
#1260000
0(
0)
0/
b1011 !
b1011 5
b1100 7
b11 6
b1100 #
b1100 &
#1265000
1)
1(
1-
b1100 !
b1100 5
b1101 7
b10 6
b1101 #
b1101 &
#1270000
0(
0-
b1101 !
b1101 5
b1110 7
b1 6
b1110 #
b1110 &
#1275000
1(
b1110 !
b1110 5
b1111 7
b0 6
b1111 #
b1111 &
#1280000
0"
0(
0)
0*
b0 7
b1 !
b1 5
b0 #
b0 &
b0 $
b0 '
1%
#1285000
1(
1+
b10 !
b10 5
b1 6
b1 #
b1 &
#1290000
0(
0+
b11 !
b11 5
b10 6
b10 #
b10 &
#1295000
1(
1)
1+
1.
b100 !
b100 5
b11 6
b11 #
b11 &
#1300000
0(
0)
0+
0.
b101 !
b101 5
b100 6
b100 #
b100 &
#1305000
1(
1+
b110 !
b110 5
b101 6
b101 #
b101 &
#1310000
0(
0+
b111 !
b111 5
b110 6
b110 #
b110 &
#1315000
1(
1)
1*
1+
1.
11
b1000 !
b1000 5
b111 6
b111 #
b111 &
#1320000
0(
0)
0*
0+
0.
01
b1001 !
b1001 5
b1000 6
b1000 #
b1000 &
#1325000
1(
1+
b1010 !
b1010 5
b1001 6
b1001 #
b1001 &
#1330000
0(
0+
b1011 !
b1011 5
b1010 6
b1010 #
b1010 &
#1335000
1(
1)
1+
1.
b1100 !
b1100 5
b1011 6
b1011 #
b1011 &
#1340000
0(
0)
0+
0.
b1101 !
b1101 5
b1100 6
b1100 #
b1100 &
#1345000
1(
1+
b1110 !
b1110 5
b1101 6
b1101 #
b1101 &
#1350000
0(
0+
b1111 !
b1111 5
b1110 6
b1110 #
b1110 &
#1355000
1"
1(
1)
1*
1,
1+
1.
11
b0 !
b0 5
b1111 6
b1111 #
b1111 &
#1360000
0"
0)
0*
0,
0.
01
b10 !
b10 5
b1 6
b0 #
b0 &
b1 $
b1 '
#1365000
0+
b11 !
b11 5
b1 7
b0 6
b1 #
b1 &
#1370000
1)
1+
1.
b100 !
b100 5
b0 7
b11 6
b10 #
b10 &
#1375000
1-
0+
0.
b101 !
b101 5
b1 7
b10 6
b11 #
b11 &
#1380000
0)
1+
0-
b110 !
b110 5
b0 7
b101 6
b100 #
b100 &
#1385000
0+
b111 !
b111 5
b1 7
b100 6
b101 #
b101 &
#1390000
1)
1*
1+
1.
11
b1000 !
b1000 5
b0 7
b111 6
b110 #
b110 &
#1395000
1-
10
0+
0.
01
b1001 !
b1001 5
b1 7
b110 6
b111 #
b111 &
#1400000
0)
0*
1+
0-
00
b1010 !
b1010 5
b0 7
b1001 6
b1000 #
b1000 &
#1405000
0+
b1011 !
b1011 5
b1 7
b1000 6
b1001 #
b1001 &
#1410000
1)
1+
1.
b1100 !
b1100 5
b0 7
b1011 6
b1010 #
b1010 &
#1415000
1-
0+
0.
b1101 !
b1101 5
b1 7
b1010 6
b1011 #
b1011 &
#1420000
0)
1+
0-
b1110 !
b1110 5
b0 7
b1101 6
b1100 #
b1100 &
#1425000
0+
b1111 !
b1111 5
b1 7
b1100 6
b1101 #
b1101 &
#1430000
1"
1)
1*
1,
1+
1.
11
b0 !
b0 5
b0 7
b1111 6
b1110 #
b1110 &
#1435000
0,
1-
10
14
0+
0.
01
b1 !
b1 5
b1 7
b1110 6
b1111 #
b1111 &
#1440000
0"
0)
0*
b11 !
b11 5
0(
0-
00
04
b10 6
b0 7
b0 #
b0 &
b10 $
b10 '
#1445000
1(
1)
1+
1.
b100 !
b100 5
b11 6
b1 #
b1 &
#1450000
0(
0+
0.
b101 !
b101 5
b10 7
b0 6
b10 #
b10 &
#1455000
1(
1+
b110 !
b110 5
b1 6
b11 #
b11 &
#1460000
0(
0+
0)
b111 !
b111 5
b0 7
b110 6
b100 #
b100 &
#1465000
1(
1)
1*
1+
1.
11
b1000 !
b1000 5
b111 6
b101 #
b101 &
#1470000
0(
0+
1/
0.
01
b1001 !
b1001 5
b10 7
b100 6
b110 #
b110 &
#1475000
1(
1+
b1010 !
b1010 5
b101 6
b111 #
b111 &
#1480000
0(
0*
0+
0)
0/
b1011 !
b1011 5
b0 7
b1010 6
b1000 #
b1000 &
#1485000
1(
1)
1+
1.
b1100 !
b1100 5
b1011 6
b1001 #
b1001 &
#1490000
0(
0+
0.
b1101 !
b1101 5
b10 7
b1000 6
b1010 #
b1010 &
#1495000
1(
1+
b1110 !
b1110 5
b1001 6
b1011 #
b1011 &
#1500000
0(
0+
0)
b1111 !
b1111 5
b0 7
b1110 6
b1100 #
b1100 &
#1505000
1"
1(
1)
1*
1,
1+
1.
11
b0 !
b0 5
b1111 6
b1101 #
b1101 &
#1510000
0(
0,
0+
1/
13
0.
01
b1 !
b1 5
b10 7
b1100 6
b1110 #
b1110 &
#1515000
1(
1+
b10 !
b10 5
b1101 6
b1111 #
b1111 &
#1520000
0"
0*
1.
0/
03
b100 !
b100 5
b0 7
b11 6
b0 #
b0 &
b11 $
b11 '
#1525000
1-
0+
0.
b101 !
b101 5
b1 7
b10 6
b1 #
b1 &
#1530000
1+
0-
b110 !
b110 5
b10 7
b1 6
b10 #
b10 &
#1535000
0+
b111 !
b111 5
b11 7
b0 6
b11 #
b11 &
