verilog_fpga_simulation/full/full.v
`timescale 1ns / 1ps

module bit_4_cla(a, b, cin, sum, cout);
    input [3:0] a, b;
    input cin;
    output [3:0] sum;
    output cout;
    wire [3:0] g, p;
    wire c1, c2, c3;

    and g0 (g[0], a[0], b[0]);
    and g1 (g[1], a[1], b[1]);
    and g2 (g[2], a[2], b[2]);
    and g3 (g[3], a[3], b[3]);

    xor p0 (p[0], a[0], b[0]);
    xor p1 (p[1], a[1], b[1]);
    xor p2 (p[2], a[2], b[2]);
    xor p3 (p[3], a[3], b[3]);

    wire temp1, temp2, temp3, temp4, temp5, temp6;

    // c1 = g0 + (p0 * cin)
    and and_c1 (temp1, p[0], cin);
    or or_c1 (c1, g[0], temp1);

    // c2 = g1 + (p1 * g0) + (p1 * p0 * cin)
    and and_c2_1 (temp2, p[1], g[0]);
    and and_c2_2 (temp3, p[1], p[0], cin);
    or or_c2 (c2, g[1], temp2, temp3);

    // c3 = g2 + (p2 * g1) + (p2 * p1 * g0) + (p2 * p1 * p0 * cin)
    and and_c3_1 (temp4, p[2], g[1]);
    and and_c3_2 (temp5, p[2], p[1], g[0]);
    and and_c3_3 (temp6, p[2], p[1], p[0], cin);
    or or_c3 (c3, g[2], temp4, temp5, temp6);

    // cout = g3 + (p3 * g2) + (p3 * p2 * g1) + (p3 * p2 * p1 * g0) + (p3 * p2 * p1 * p0 * cin)
    wire temp7, temp8, temp9, temp10;
    and and_cout_1 (temp7, p[3], g[2]);
    and and_cout_2 (temp8, p[3], p[2], g[1]);
    and and_cout_3 (temp9, p[3], p[2], p[1], g[0]);
    and and_cout_4 (temp10, p[3], p[2], p[1], p[0], cin);
    or or_cout (cout, g[3], temp7, temp8, temp9, temp10);

    xor sum0 (sum[0], p[0], cin);
    xor sum1 (sum[1], p[1], c1);
    xor sum2 (sum[2], p[2], c2);
    xor sum3 (sum[3], p[3], c3);
endmodule

module d_ff(d,clk,q);
    input d,clk;
    output reg q;
    always@(posedge clk) begin
        q <= d;
    end
endmodule

module full (
    input clk,           // Clock signal for all D flip-flops
    input [3:0] A_in,    // 4-bit input number A
    input [3:0] B_in,    // 4-bit input number B
    input C0_in,         // Carry-in
    output [3:0] S_out,  // 4-bit output sum
    output C4_out        // Carry-out
);
    // Internal signals
    wire [3:0] A_reg, B_reg; // Outputs of input D flip-flops for A and B
    wire C0_reg;             // Output of input D flip-flop for C0
    wire [3:0] S_wire;       // Outputs from the 4-bit CLA
    wire Cout_wire;          // Carry-out from the 4-bit CLA

    // 4 D flip-flops for input A
    d_ff dff_a0 (.clk(clk), .d(A_in[0]), .q(A_reg[0]));
    d_ff dff_a1 (.clk(clk), .d(A_in[1]), .q(A_reg[1]));
    d_ff dff_a2 (.clk(clk), .d(A_in[2]), .q(A_reg[2]));
    d_ff dff_a3 (.clk(clk), .d(A_in[3]), .q(A_reg[3]));

    // 4 D flip-flops for input B
    d_ff dff_b0 (.clk(clk), .d(B_in[0]), .q(B_reg[0]));
    d_ff dff_b1 (.clk(clk), .d(B_in[1]), .q(B_reg[1]));
    d_ff dff_b2 (.clk(clk), .d(B_in[2]), .q(B_reg[2]));
    d_ff dff_b3 (.clk(clk), .d(B_in[3]), .q(B_reg[3]));

    // 1 D flip-flop for input C0
    d_ff dff_c0 (.clk(clk), .d(C0_in), .q(C0_reg));

    // 4-bit Carry-Lookahead Adder
    bit_4_cla cla (
        .a(A_reg),
        .b(B_reg),
        .cin(C0_reg),
        .sum(S_wire),
        .cout(Cout_wire)
    );

    // 4 D flip-flops for output S
    d_ff dff_s0 (.clk(clk), .d(S_wire[0]), .q(S_out[0]));
    d_ff dff_s1 (.clk(clk), .d(S_wire[1]), .q(S_out[1]));
    d_ff dff_s2 (.clk(clk), .d(S_wire[2]), .q(S_out[2]));
    d_ff dff_s3 (.clk(clk), .d(S_wire[3]), .q(S_out[3]));

    // 1 D flip-flop for output C4
    d_ff dff_c4 (.clk(clk), .d(Cout_wire), .q(C4_out));

endmodule

fpga_simulation/full/full_test.v
`timescale 1ns / 1ps

module full_test;
    reg clk;
    reg [3:0] A_in, B_in;
    reg C0_in;
    wire [3:0] S_out;
    wire C4_out;

    full uut (
        .clk(clk),
        .A_in(A_in),
        .B_in(B_in),
        .C0_in(C0_in),
        .S_out(S_out),
        .C4_out(C4_out)
    );

    initial begin
        $dumpfile("full_test.vcd");
        $dumpvars(0,full_test);
        clk = 1'b0;
        forever #5 clk = ~clk;
    end

    initial begin
        A_in = 0; B_in = 0; C0_in = 0;
        #3 A_in = 4'b1010; B_in = 4'b0111; C0_in = 1;
        #10 A_in = 4'b1100; B_in = 4'b0011; C0_in = 0;
        #10 A_in = 4'b1111; B_in = 4'b1111; C0_in = 1;
        #20 $finish;
    end

    initial begin
        $monitor("Time = %0t, A = %b, B = %b, C0 = %b, S = %b, C4 = %b",
                 $time, A_in, B_in, C0_in, S_out, C4_out);
    end
endmodule

fpga_simulation/full/full_test.vcd
$date
	Wed Nov 20 01:04:45 2024
$end
$version
	Icarus Verilog
$end
$timescale
	1ps
$end
$scope module full_test $end
$var wire 4 ! S_out [3:0] $end
$var wire 1 " C4_out $end
$var reg 4 # A_in [3:0] $end
$var reg 4 $ B_in [3:0] $end
$var reg 1 % C0_in $end
$var reg 1 & clk $end
$scope module uut $end
$var wire 4 ' A_in [3:0] $end
$var wire 4 ( B_in [3:0] $end
$var wire 1 % C0_in $end
$var wire 1 & clk $end
$var wire 4 ) S_wire [3:0] $end
$var wire 4 * S_out [3:0] $end
$var wire 1 + Cout_wire $end
$var wire 1 " C4_out $end
$var wire 1 , C0_reg $end
$var wire 4 - B_reg [3:0] $end
$var wire 4 . A_reg [3:0] $end
$scope module cla $end
$var wire 4 / a [3:0] $end
$var wire 4 0 b [3:0] $end
$var wire 1 1 c1 $end
$var wire 1 2 c2 $end
$var wire 1 3 c3 $end
$var wire 1 + cout $end
$var wire 1 4 temp1 $end
$var wire 1 5 temp10 $end
$var wire 1 6 temp2 $end
$var wire 1 7 temp3 $end
$var wire 1 8 temp4 $end
$var wire 1 9 temp5 $end
$var wire 1 : temp6 $end
$var wire 1 ; temp7 $end
$var wire 1 < temp8 $end
$var wire 1 = temp9 $end
$var wire 4 > sum [3:0] $end
$var wire 4 ? p [3:0] $end
$var wire 4 @ g [3:0] $end
$var wire 1 , cin $end
$upscope $end
$scope module dff_a0 $end
$var wire 1 & clk $end
$var wire 1 A d $end
$var reg 1 B q $end
$upscope $end
$scope module dff_a1 $end
$var wire 1 & clk $end
$var wire 1 C d $end
$var reg 1 D q $end
$upscope $end
$scope module dff_a2 $end
$var wire 1 & clk $end
$var wire 1 E d $end
$var reg 1 F q $end
$upscope $end
$scope module dff_a3 $end
$var wire 1 & clk $end
$var wire 1 G d $end
$var reg 1 H q $end
$upscope $end
$scope module dff_b0 $end
$var wire 1 & clk $end
$var wire 1 I d $end
$var reg 1 J q $end
$upscope $end
$scope module dff_b1 $end
$var wire 1 & clk $end
$var wire 1 K d $end
$var reg 1 L q $end
$upscope $end
$scope module dff_b2 $end
$var wire 1 & clk $end
$var wire 1 M d $end
$var reg 1 N q $end
$upscope $end
$scope module dff_b3 $end
$var wire 1 & clk $end
$var wire 1 O d $end
$var reg 1 P q $end
$upscope $end
$scope module dff_c0 $end
$var wire 1 & clk $end
$var wire 1 % d $end
$var reg 1 , q $end
$upscope $end
$scope module dff_c4 $end
$var wire 1 & clk $end
$var wire 1 + d $end
$var reg 1 " q $end
$upscope $end
$scope module dff_s0 $end
$var wire 1 & clk $end
$var wire 1 Q d $end
$var reg 1 R q $end
$upscope $end
$scope module dff_s1 $end
$var wire 1 & clk $end
$var wire 1 S d $end
$var reg 1 T q $end
$upscope $end
$scope module dff_s2 $end
$var wire 1 & clk $end
$var wire 1 U d $end
$var reg 1 V q $end
$upscope $end
$scope module dff_s3 $end
$var wire 1 & clk $end
$var wire 1 W d $end
$var reg 1 X q $end
$upscope $end
$upscope $end
$upscope $end
$enddefinitions $end
#0
$dumpvars
xX
xW
xV
xU
xT
xS
xR
xQ
xP
0O
xN
0M
xL
0K
xJ
0I
xH
0G
xF
0E
xD
0C
xB
0A
bx @
bx ?
bx >
x=
x<
x;
x:
x9
x8
x7
x6
x5
x4
x3
x2
x1
bx 0
bx /
bx .
bx -
x,
x+
bx *
bx )
b0 (
b0 '
0&
0%
b0 $
b0 #
x"
bx !
$end
#3000
1I
1K
1M
1C
1G
1%
b111 $
b111 (
b1010 #
b1010 '
#5000
1S
0U
0W
0Q
1+
05
11
14
b10 )
b10 >
12
06
07
13
18
09
0:
0;
1<
0=
b10 @
b1101 ?
0B
1D
0F
b1010 .
b1010 /
1H
1J
1L
1N
b111 -
b111 0
0P
1,
1&
#10000
0&
#13000
0M
0C
1E
0%
b11 $
b11 (
b1100 #
b1100 '
#15000
1W
1U
0+
03
02
08
0<
1Q
01
b0 @
b1111 ?
b1111 )
b1111 >
04
1"
0X
0V
1T
b10 !
b10 *
0R
0,
b11 -
b11 0
0N
1F
b1100 .
b1100 /
0D
1&
#20000
0&
#23000
1M
1O
1A
1C
1%
b1111 $
b1111 (
b1111 #
b1111 '
#25000
1+
1W
1U
1S
b1111 @
b0 ?
1Q
05
13
12
11
b1111 )
b1111 >
0:
07
04
1B
b1111 .
b1111 /
1D
1N
b1111 -
b1111 0
1P
1,
1R
1V
b1111 !
b1111 *
1X
0"
1&
#30000
0&
#35000
1"
1&
